[
  {
    "_id": "emp001",
    "name": "Alice Smith",
    "email": "alice.smith@example.com",
    "skills": ["Node.js", "React", "MongoDB"],
    "department": "Engineering",
    "position": "Full Stack Engineer",
    "experience_level": "Mid",
    "current_projects": ["proj001"],
    "capacity_hours": 38,
    "location": "Bangalore",
    "performance_score": 4.0,
    "last_updated": "2025-09-19T00:00:00Z"
  },
  {
    "_id": "emp002",
    "name": "Bob Smith",
    "email": "bob.smith@example.com",
    "skills": ["Java", "Spring", "Docker"],
    "department": "Engineering",
    "position": "Lead Developer",
    "experience_level": "Senior",
    "current_projects": ["proj001"],
    "capacity_hours": 40,
    "location": "San Francisco",
    "performance_score": 4.2,
    "last_updated": "2025-09-19T00:00:00Z"
  },
  {
    "_id": "emp003",
    "name": "Carol Williams",
    "email": "carol.williams@example.com",
    "skills": ["Figma", "Prototyping", "User Research"],
    "department": "Design",
    "position": "UI/UX Designer",
    "experience_level": "Mid",
    "current_projects": ["proj002", "proj003"],
    "capacity_hours": 35,
    "location": "Remote",
    "performance_score": 3.9,
    "last_updated": "2025-09-19T00:00:00Z"
  },
  {
    "_id": "emp004",
    "name": "David Lee",
    "email": "david.lee@example.com",
    "skills": ["DevOps", "AWS", "Docker", "CI/CD"],
    "department": "Platform",
    "position": "DevOps Engineer",
    "experience_level": "Senior",
    "current_projects": ["proj004"],
    "capacity_hours": 36,
    "location": "Hyderabad",
    "performance_score": 4.5,
    "last_updated": "2025-09-19T00:00:00Z"
  },
  {
    "_id": "emp005",
    "name": "Eva Johnson",
    "email": "eva.johnson@example.com",
    "skills": ["Python", "Pandas", "SQL"],
    "department": "Data",
    "position": "Data Analyst",
    "experience_level": "Junior",
    "current_projects": ["proj005"],
    "capacity_hours": 40,
    "location": "Pune",
    "performance_score": 3.6,
    "last_updated": "2025-09-19T00:00:00Z"
  },
  {
    "_id": "emp006",
    "name": "Frank Miller",
    "email": "frank.miller@example.com",
    "skills": ["Kubernetes", "Terraform", "Prometheus"],
    "department": "Platform",
    "position": "SRE",
    "experience_level": "Senior",
    "current_projects": ["proj004", "proj006"],
    "capacity_hours": 37,
    "location": "Berlin",
    "performance_score": 4.4,
    "last_updated": "2025-09-19T00:00:00Z"
  },
  {
    "_id": "emp007",
    "name": "Grace Kim",
    "email": "grace.kim@example.com",
    "skills": ["Vue", "TypeScript", "UX"],
    "department": "Engineering",
    "position": "Frontend Engineer",
    "experience_level": "Mid",
    "current_projects": ["proj007"],
    "capacity_hours": 39,
    "location": "Toronto",
    "performance_score": 4.1,
    "last_updated": "2025-09-19T00:00:00Z"
  },
  {
    "_id": "emp008",
    "name": "Henry Patel",
    "email": "henry.patel@example.com",
    "skills": ["Django", "PostgreSQL", "Redis"],
    "department": "Engineering",
    "position": "Backend Engineer",
    "experience_level": "Mid",
    "current_projects": ["proj008"],
    "capacity_hours": 40,
    "location": "Delhi",
    "performance_score": 3.8,
    "last_updated": "2025-09-19T00:00:00Z"
  },
  {
    "_id": "emp009",
    "name": "Ivy Chen",
    "email": "ivy.chen@example.com",
    "skills": ["Jest", "Cypress", "QA"],
    "department": "QA",
    "position": "QA Engineer",
    "experience_level": "Junior",
    "current_projects": ["proj009"],
    "capacity_hours": 40,
    "location": "Bangalore",
    "performance_score": 3.5,
    "last_updated": "2025-09-19T00:00:00Z"
  },
  {
    "_id": "emp010",
    "name": "Jack Wilson",
    "email": "jack.wilson@example.com",
    "skills": ["AWS", "Lambda", "API Gateway"],
    "department": "Engineering",
    "position": "Cloud Architect",
    "experience_level": "Lead",
    "current_projects": ["proj010", "proj001"],
    "capacity_hours": 34,
    "location": "London",
    "performance_score": 4.7,
    "last_updated": "2025-09-19T00:00:00Z"
  },
  {
    "_id": "emp011",
    "name": "Kathy Brown",
    "email": "kathy.brown@example.com",
    "skills": ["TensorFlow", "Python", "ML"],
    "department": "Data",
    "position": "ML Engineer",
    "experience_level": "Senior",
    "current_projects": ["proj005", "proj011"],
    "capacity_hours": 36,
    "location": "San Francisco",
    "performance_score": 4.3,
    "last_updated": "2025-09-19T00:00:00Z"
  },
  {
    "_id": "emp012",
    "name": "Liam Martinez",
    "email": "liam.martinez@example.com",
    "skills": ["Go", "gRPC", "Microservices"],
    "department": "Engineering",
    "position": "Backend Engineer",
    "experience_level": "Mid",
    "current_projects": ["proj012"],
    "capacity_hours": 40,
    "location": "Remote",
    "performance_score": 4.0,
    "last_updated": "2025-09-19T00:00:00Z"
  },
  {
    "_id": "emp013",
    "name": "Maya Gupta",
    "email": "maya.gupta@example.com",
    "skills": ["Illustrator", "Branding", "Figma"],
    "department": "Design",
    "position": "Product Designer",
    "experience_level": "Senior",
    "current_projects": ["proj003"],
    "capacity_hours": 32,
    "location": "Pune",
    "performance_score": 4.6,
    "last_updated": "2025-09-19T00:00:00Z"
  },
  {
    "_id": "emp014",
    "name": "Noah Davis",
    "email": "noah.davis@example.com",
    "skills": ["Scrum", "Jira", "Agile"],
    "department": "Product",
    "position": "Scrum Master",
    "experience_level": "Mid",
    "current_projects": ["proj010", "proj014"],
    "capacity_hours": 35,
    "location": "Toronto",
    "performance_score": 4.1,
    "last_updated": "2025-09-19T00:00:00Z"
  },
  {
    "_id": "emp015",
    "name": "Olivia Perez",
    "email": "olivia.perez@example.com",
    "skills": ["Excel", "Accounting", "SAP"],
    "department": "Finance",
    "position": "Finance Analyst",
    "experience_level": "Junior",
    "current_projects": ["proj015"],
    "capacity_hours": 40,
    "location": "New York",
    "performance_score": 3.7,
    "last_updated": "2025-09-19T00:00:00Z"
  },
  {
    "_id": "emp016",
    "name": "Paul Anderson",
    "email": "paul.anderson@example.com",
    "skills": ["Salesforce", "Negotiation", "CRM"],
    "department": "Sales",
    "position": "Sales Executive",
    "experience_level": "Mid",
    "current_projects": ["proj016"],
    "capacity_hours": 39,
    "location": "London",
    "performance_score": 3.9,
    "last_updated": "2025-09-19T00:00:00Z"
  },
  {
    "_id": "emp017",
    "name": "Quinn Rogers",
    "email": "quinn.rogers@example.com",
    "skills": ["Android", "Kotlin", "Jetpack"],
    "department": "Engineering",
    "position": "Mobile Developer",
    "experience_level": "Senior",
    "current_projects": ["proj017", "proj001"],
    "capacity_hours": 34,
    "location": "Delhi",
    "performance_score": 4.2,
    "last_updated": "2025-09-19T00:00:00Z"
  },
  {
    "_id": "emp018",
    "name": "Rita Singh",
    "email": "rita.singh@example.com",
    "skills": ["People Ops", "Onboarding", "Compliance"],
    "department": "HR",
    "position": "HR Generalist",
    "experience_level": "Mid",
    "current_projects": ["proj018"],
    "capacity_hours": 40,
    "location": "Hyderabad",
    "performance_score": 3.8,
    "last_updated": "2025-09-19T00:00:00Z"
  },
  {
    "_id": "emp019",
    "name": "Samir Khan",
    "email": "samir.khan@example.com",
    "skills": ["Security", "OWASP", "SIEM"],
    "department": "Engineering",
    "position": "Security Engineer",
    "experience_level": "Senior",
    "current_projects": ["proj019"],
    "capacity_hours": 33,
    "location": "Berlin",
    "performance_score": 4.6,
    "last_updated": "2025-09-19T00:00:00Z"
  },
  {
    "_id": "emp020",
    "name": "Tina Alvarez",
    "email": "tina.alvarez@example.com",
    "skills": ["Content", "SEO", "Analytics"],
    "department": "Marketing",
    "position": "Content Strategist",
    "experience_level": "Junior",
    "current_projects": ["proj020"],
    "capacity_hours": 40,
    "location": "Remote",
    "performance_score": 3.4,
    "last_updated": "2025-09-19T00:00:00Z"
  }
]
